dash_yada/Yada.py
dash_yada/__init__.py
dash_yada/_imports_.py
dash_yada/package-info.json
dash_yada/tech-support.png
dash_yada/yada.css
dash_yada/yada.gif
dash_yada/yada.js
dash_yada/yada.png
dash_yada/yada_headshot.png
dash_yada-0.0.1.dist-info/LICENSE
dash_yada-0.0.1.dist-info/METADATA
dash_yada-0.0.1.dist-info/WHEEL
dash_yada-0.0.1.dist-info/top_level.txt
dash_yada-0.0.1.dist-info/RECORD
